fritz_switch_profiles/__init__.py
fritz_switch_profiles/fritz_switch_profiles.py
fritz_switch_profiles-1.1.5.dist-info/LICENSE
fritz_switch_profiles-1.1.5.dist-info/WHEEL
fritz_switch_profiles-1.1.5.dist-info/METADATA
fritz_switch_profiles-1.1.5.dist-info/RECORD
