Metadata-Version: 2.1
Name: fritz-switch-profiles
Version: 1.1.5
Summary: fritz_switch_profiles
Home-page: http://github.com/eifinger/fritz-switch-profiles
Author: eifinger
Author-email: k.eifinger@googlemail.com
Requires-Python: >=3.6
Classifier: Intended Audience :: Developers
Classifier: Operating System :: OS Independent
Classifier: Programming Language :: Python
Classifier: Programming Language :: Python :: 3
Classifier: Topic :: Software Development :: Libraries :: Python Modules
Classifier: License :: OSI Approved :: MIT License
Requires-Dist: requests
Requires-Dist: lxml
Requires-Dist: pylint ; extra == "test"
Requires-Dist: flake8 ; extra == "test"
Requires-Dist: mypy ; extra == "test"
Requires-Dist: pre-commit ; extra == "test"
Requires-Dist: black ; extra == "test"
Provides-Extra: test
